README.md
setup.py
nomad_connectors_cli/__init__.py
nomad_connectors_cli/api_client.py
nomad_connectors_cli/append_alibaba_headers.py
nomad_connectors_cli/configuration.py
nomad_connectors_cli/exceptions.py
nomad_connectors_cli/rest.py
nomad_connectors_cli/rest_bak.py
nomad_connectors_cli/swagger_validator.py
nomad_connectors_cli.egg-info/PKG-INFO
nomad_connectors_cli.egg-info/SOURCES.txt
nomad_connectors_cli.egg-info/dependency_links.txt
nomad_connectors_cli.egg-info/requires.txt
nomad_connectors_cli.egg-info/top_level.txt
nomad_connectors_cli/api/__init__.py
nomad_connectors_cli/api/customs_callback_api.py
nomad_connectors_cli/api/customs_order_api.py
nomad_connectors_cli/api/customs_payment_api.py
nomad_connectors_cli/api/customs_product_api.py
nomad_connectors_cli/api/order_api.py
nomad_connectors_cli/api/product_api.py
nomad_connectors_cli/api/ship_api.py
nomad_connectors_cli/models/__init__.py
nomad_connectors_cli/models/address.py
nomad_connectors_cli/models/api_response.py
nomad_connectors_cli/models/api_response_connector_response.py
nomad_connectors_cli/models/api_response_data.py
nomad_connectors_cli/models/customs_declaration_result.py
nomad_connectors_cli/models/dimension.py
nomad_connectors_cli/models/goldjet.py
nomad_connectors_cli/models/images.py
nomad_connectors_cli/models/order.py
nomad_connectors_cli/models/order_product.py
nomad_connectors_cli/models/package.py
nomad_connectors_cli/models/package_item.py
nomad_connectors_cli/models/product.py
nomad_connectors_cli/models/product_sku.py
test/__init__.py
test/test_address.py
test/test_api_response.py
test/test_api_response_connector_response.py
test/test_api_response_data.py
test/test_customs_callback_api.py
test/test_customs_declaration_result.py
test/test_customs_order_api.py
test/test_customs_payment_api.py
test/test_customs_product_api.py
test/test_dimension.py
test/test_goldjet.py
test/test_images.py
test/test_order.py
test/test_order_api.py
test/test_order_product.py
test/test_package.py
test/test_package_item.py
test/test_product.py
test/test_product_api.py
test/test_product_sku.py
test/test_ship_api.py