Metadata-Version: 1.0
Name: nomad-connectors-cli
Version: 0.1.0
Summary: Nomad Envoy/Pilot
Home-page: UNKNOWN
Author: UNKNOWN
Author-email: paul@samarkand.global
License: UNKNOWN
Keywords: OpenAPI,OpenAPI-Generator,Nomad Envoy/Pilot
Platform: UNKNOWN
